Workbook
Name SalesTaxRate: Lookups!$B$2

Sheet Dashboard
A1: Quarterly Sales Dashboard
A3: Measure | B3: Value | D3: Region | E3: Revenue
A4: Gross Revenue | B4: =SUM(Transactions!F4:F11) -> 3793.1 | D4: North | E4: =SUMIF(Transactions!$B$4:$B$11,D4,Transactions!$F$4:$F$11) -> 989.4
A5: Tax | B5: =SUM(Transactions!G4:G11) -> 493.103 | D5: South | E5: =SUMIF(Transactions!$B$4:$B$11,D5,Transactions!$F$4:$F$11) -> 840
A6: Net Total | B6: =SUM(Transactions!H4:H11) -> 4286.203 | D6: East | E6: =SUMIF(Transactions!$B$4:$B$11,D6,Transactions!$F$4:$F$11) -> 1231.65
D7: West | E7: =SUMIF(Transactions!$B$4:$B$11,D7,Transactions!$F$4:$F$11) -> 732.05

Sheet Transactions
A3: Date | B3: Region | C3: Product | D3: Units | E3: Unit Price | F3: Revenue | G3: Tax | H3: Net
A4: 46027 | B4: North | C4: Widget A | D4: 12 | E4: 19.95 | F4: =D4*E4 -> 239.4 | G4: =F4*SalesTaxRate -> 31.122 | H4: =F4+G4 -> 270.522
A5: 46034 | B5: South | C5: Widget B | D5: 8 | E5: 42.5 | F5: =D5*E5 -> 340 | G5: =F5*SalesTaxRate -> 44.2 | H5: =F5+G5 -> 384.2
A6: 46041 | B6: East | C6: Widget A | D6: 17 | E6: 19.95 | F6: =D6*E6 -> 339.15 | G6: =F6*SalesTaxRate -> 44.0895 | H6: =F6+G6 -> 383.2395
A7: 46055 | B7: North | C7: Widget C | D7: 6 | E7: 125 | F7: =D7*E7 -> 750 | G7: =F7*SalesTaxRate -> 97.5 | H7: =F7+G7 -> 847.5
A8: 46062 | B8: West | C8: Widget B | D8: 13 | E8: 42.5 | F8: =D8*E8 -> 552.5 | G8: =F8*SalesTaxRate -> 71.825 | H8: =F8+G8 -> 624.325
A9: 46069 | B9: South | C9: Widget C | D9: 4 | E9: 125 | F9: =D9*E9 -> 500 | G9: =F9*SalesTaxRate -> 65 | H9: =F9+G9 -> 565
A10: 46083 | B10: East | C10: Widget B | D10: 21 | E10: 42.5 | F10: =D10*E10 -> 892.5 | G10: =F10*SalesTaxRate -> 116.025 | H10: =F10+G10 -> 1008.525
A11: 46090 | B11: West | C11: Widget A | D11: 9 | E11: 19.95 | F11: =D11*E11 -> 179.55 | G11: =F11*SalesTaxRate -> 23.3415 | H11: =F11+G11 -> 202.8915

Sheet Lookups
A1: Parameter | B1: Value | D1: Product Catalog
A2: Sales tax | B2: 0.13 | D2: Widget A
A3: Currency | B3: USD | D3: Widget B
D4: Widget C
